README
qrcgen.py
setup.py
qrcgen.egg-info/PKG-INFO
qrcgen.egg-info/SOURCES.txt
qrcgen.egg-info/dependency_links.txt
qrcgen.egg-info/top_level.txt
qrcgen.egg-info/zip-safe