Metadata-Version: 1.0
Name: qrcgen
Version: 0.2
Summary: Automated generator of Qt resource files (*.qrc), by recursive scanning of directory trees
Home-page: http://github.com/fccoelho/qrcgen
Author: Flavio Codeco Coelho
Author-email: fccoelho@gmail.com
License: GPLv3
Platform: UNKNOWN
